ab_core/sqlalchemy_fastapi_http_exceptions/__init__.py
ab_core/sqlalchemy_fastapi_http_exceptions/fastapi_integration.py
ab_core/sqlalchemy_fastapi_http_exceptions/handlers.py
ab_core/sqlalchemy_fastapi_http_exceptions/dialects/__init__.py
ab_core/sqlalchemy_fastapi_http_exceptions/dialects/ansi.py
ab_core/sqlalchemy_fastapi_http_exceptions/dialects/base.py
ab_core/sqlalchemy_fastapi_http_exceptions/dialects/db2.py
ab_core/sqlalchemy_fastapi_http_exceptions/dialects/hana.py
ab_core/sqlalchemy_fastapi_http_exceptions/dialects/mssql.py
ab_core/sqlalchemy_fastapi_http_exceptions/dialects/mysql.py
ab_core/sqlalchemy_fastapi_http_exceptions/dialects/oracle.py
ab_core/sqlalchemy_fastapi_http_exceptions/dialects/postgres.py
ab_core/sqlalchemy_fastapi_http_exceptions/dialects/sqlite.py
ab_sqlalchemy_fastapi_http_exceptions-0.1.2.dist-info/METADATA
ab_sqlalchemy_fastapi_http_exceptions-0.1.2.dist-info/WHEEL
ab_sqlalchemy_fastapi_http_exceptions-0.1.2.dist-info/licenses/LICENSE
ab_sqlalchemy_fastapi_http_exceptions-0.1.2.dist-info/RECORD
