Metadata-Version: 2.4
Name: ab-sqlalchemy-fastapi-http-exceptions
Version: 0.1.2
Summary: A template package template.
Author-email: Matt Coulter <mattcoul7@gmail.com>
License-File: LICENSE
Requires-Python: <4.0,>=3.12
Requires-Dist: ab-database<0.3.0,>=0.2.2
Requires-Dist: ab-dependency<0.3.0,>=0.2.0
Requires-Dist: fastapi<0.116,>=0.115.0
Requires-Dist: pydantic>=2.12.0
Requires-Dist: sqlalchemy>=2.0.0
